{
  "name": "Pagination",
  "description": "Use pagination to let merchants move through an ordered collection of items that has been split into pages. On the web, pagination uses buttons to move back and forth between pages. On iOS and Android, pagination uses infinite scrolling.",
  "bestPractices": "On all platforms, pagination should:\n\n- Only be used for lists with more than 25 items\n\nWeb pagination should:\n\n- Be placed at the bottom of a long list that has been split up into pages\n- Pagination should navigate to the previous and next set of items in the paged list\n- Hint when merchants are at the first or the last page by disabling the corresponding button\n\niOS and Android pagination should:\n\n- Start loading items when merchants are close to the bottom, roughly 5 items from the end\n- Show [a spinner](https://polaris.shopify.com/components/spinner) below the list to indicate that items have been requested",
  "keywords": [
    " lists\n  ",
    " detail\n  ",
    " page\n  ",
    " label\n  ",
    " pager\n  ",
    " previous\n  ",
    " next\n  ",
    " navigation between pages\n  ",
    " page arrows\n  ",
    " list navigation\n  ",
    " list arrows\n  ",
    " list pagination\n  ",
    " list pages\n  ",
    " previous next buttons\n  ",
    " previous buttons\n  ",
    " next buttons"
  ],
  "previewImg": "pagination.png"
}