{
  "filePath": "src/components/IndexFilters/types.ts",
  "name": "SortButtonChoice",
  "description": "",
  "value": "export interface SortButtonChoice {\n  label: string;\n  disabled?: boolean;\n  value: SortValue;\n  directionLabel: string;\n}",
  "members": [
    {
      "filePath": "src/components/IndexFilters/types.ts",
      "syntaxKind": "PropertySignature",
      "name": "label",
      "value": "string",
      "description": ""
    },
    {
      "filePath": "src/components/IndexFilters/types.ts",
      "syntaxKind": "PropertySignature",
      "name": "disabled",
      "value": "boolean",
      "description": "",
      "isOptional": true
    },
    {
      "filePath": "src/components/IndexFilters/types.ts",
      "syntaxKind": "PropertySignature",
      "name": "value",
      "value": "`${string} asc` | `${string} desc`",
      "description": ""
    },
    {
      "filePath": "src/components/IndexFilters/types.ts",
      "syntaxKind": "PropertySignature",
      "name": "directionLabel",
      "value": "string",
      "description": ""
    }
  ]
}